teenygrad/__init__.py
teenygrad-0.1.0.dist-info/licenses/LICENSE
teenygrad-0.1.0.dist-info/METADATA
teenygrad-0.1.0.dist-info/WHEEL
teenygrad-0.1.0.dist-info/top_level.txt
teenygrad-0.1.0.dist-info/RECORD
