Metadata-Version: 2.4
Name: teenygrad
Version: 0.1.0
Summary: Teenygrad JIT compiler.
Author: Arshad M
Author-email: Arshad M <arshadm@teenygrad.org>
Classifier: Programming Language :: Python :: 3
Classifier: Operating System :: OS Independent
Requires-Python: >=3.7
License-File: LICENSE
Dynamic: license-file
